Metadata-Version: 2.0
Name: odoo8-addon-l10n-es-account-balance-report
Version: 8.0.0.1.0.99.dev4
Summary: Informes de cuentas anuales españoles
Home-page: http://www.pexego.es
Author: Pexego, Zikzakmedia,Odoo Community Association (OCA)
Author-email: support@odoo-community.org
License: AGPL-3
Platform: UNKNOWN
Classifier: Programming Language :: Python
Classifier: Framework :: Odoo
Classifier: License :: OSI Approved :: GNU Affero General Public License v3
Requires-Python: ~=2.7
Requires-Dist: odoo (<9.0a,>=8.0a)
Requires-Dist: odoo8-addon-account-balance-reporting
